setup.cfg
setup.py
cockatiel/__init__.py
cockatiel/__main__.py
cockatiel/config.py
cockatiel/handlers.py
cockatiel/queue.py
cockatiel/replication.py
cockatiel/server.py
cockatiel.egg-info/PKG-INFO
cockatiel.egg-info/SOURCES.txt
cockatiel.egg-info/dependency_links.txt
cockatiel.egg-info/requires.txt
cockatiel.egg-info/top_level.txt
cockatiel/utils/__init__.py
cockatiel/utils/filenames.py
cockatiel/utils/streams.py