Metadata-Version: 1.1
Name: cockatiel
Version: 0.0.2
Summary: Simple replicated file storage
Home-page: https://github.com/raphaelm/cockatiel
Author: Raphael Michel
Author-email: mail@raphaelmichel.de
License: Apache License 2.0
Keywords: django file storage media backend replicated
Platform: UNKNOWN
Classifier: Development Status :: 3 - Alpha
Classifier: Intended Audience :: Developers
Classifier: Intended Audience :: Other Audience
Classifier: License :: OSI Approved :: Apache Software License
Classifier: Programming Language :: Python :: 3.4
Classifier: Programming Language :: Python :: 3.5
